{
    "services": [
      {
        "name": "bttg_api_cluster",
        "auth_token": "u8x2k9ab3m4q7z1p0r5t6y2w3e4r8t9y",
        "secret_key": "sk_live_92jd82k2k29d8dj2k2k2",
        "username": "admin_api",
        "password": "P@ssw0rd123!"
      },
      {
        "name": "database_bttg",
        "auth_token": "dbtoken_72hs8s8s9s9s",
        "secret_key": "db_secret_abc123xyz",
        "username": "root",
        "password": "root1234"
      },
      {
        "name": "internal_panel",
        "auth_token": "int_9992jd82jd82jd",
        "secret_key": "panel_secret_888",
        "username": "admin",
        "password": "admin"
      },
      {
        "name": "third_party",
        "auth_token": "tp_123abc456def",
        "secret_key": "thirdparty_secret_key",
        "username": "user_test",
        "password": "test@123"
      }
    ]
  }
